CHANGELOG.md
LICENSE
MANIFEST.in
README.md
pyproject.toml
setup.cfg
setup.py
src/pytest_inmanta_lsm/__init__.py
src/pytest_inmanta_lsm/exceptions.py
src/pytest_inmanta_lsm/failed_resources_logs.py
src/pytest_inmanta_lsm/load_generator.py
src/pytest_inmanta_lsm/lsm_project.py
src/pytest_inmanta_lsm/managed_service_instance.py
src/pytest_inmanta_lsm/orchestrator_container.py
src/pytest_inmanta_lsm/parameters.py
src/pytest_inmanta_lsm/plugin.py
src/pytest_inmanta_lsm/py.typed
src/pytest_inmanta_lsm/remote_orchestrator.py
src/pytest_inmanta_lsm/remote_service_instance.py
src/pytest_inmanta_lsm/remote_service_instance.pyi
src/pytest_inmanta_lsm/remote_service_instance_async.py
src/pytest_inmanta_lsm/util.py
src/pytest_inmanta_lsm/wait_for_state.py
src/pytest_inmanta_lsm.egg-info/PKG-INFO
src/pytest_inmanta_lsm.egg-info/SOURCES.txt
src/pytest_inmanta_lsm.egg-info/dependency_links.txt
src/pytest_inmanta_lsm.egg-info/entry_points.txt
src/pytest_inmanta_lsm.egg-info/requires.txt
src/pytest_inmanta_lsm.egg-info/top_level.txt
src/pytest_inmanta_lsm/resources/docker-compose-http-license.yml
src/pytest_inmanta_lsm/resources/docker-compose-legacy.yml
src/pytest_inmanta_lsm/resources/docker-compose.yml
src/pytest_inmanta_lsm/resources/my-env-file
src/pytest_inmanta_lsm/resources/my-server-conf.cfg
src/pytest_inmanta_lsm/resources/setup_project.py
tests/test_examples_quickstart.py
tests/test_examples_test_service.py
tests/test_multi_version.py
tests/test_partial.py