Metadata-Version: 2.4
Name: pytest-inmanta-lsm
Version: 4.0.0
Summary: Common fixtures for inmanta LSM related modules
Home-page: https://github.com/inmanta/pytest-inmanta-lsm
Author: Inmanta
Author-email: code@inmanta.com
License: inmanta EULA
Classifier: Development Status :: 5 - Production/Stable
Classifier: Framework :: Pytest
Classifier: Intended Audience :: Developers
Classifier: Programming Language :: Python :: 3.11
Classifier: Programming Language :: Python :: 3.12
Classifier: Operating System :: OS Independent
Classifier: Topic :: Software Development :: Testing
Classifier: Topic :: System :: Systems Administration
Classifier: Topic :: Utilities
Requires-Python: >=3.11
License-File: LICENSE
Requires-Dist: pytest-inmanta<5.0,>=2.5
Requires-Dist: inmanta-lsm
Requires-Dist: devtools
Dynamic: author
Dynamic: author-email
Dynamic: classifier
Dynamic: description
Dynamic: description-content-type
Dynamic: home-page
Dynamic: license
Dynamic: license-file
Dynamic: requires-dist
Dynamic: requires-python
Dynamic: summary
